data_preprocessing_library/__init__.py
data_preprocessing_library/categorical_encoder.py
data_preprocessing_library/data_time_handler.py
data_preprocessing_library/data_type_converter.py
data_preprocessing_library/feature_engineer.py
data_preprocessing_library/missing_value_handler.py
data_preprocessing_library/outlier_handler.py
data_preprocessing_library/scaler.py
data_preprocessing_library/test_data_preprocessing.py
data_preprocessing_library/text_cleaner.py
data_preprocessing_library-0.1.0.dist-info/METADATA
data_preprocessing_library-0.1.0.dist-info/WHEEL
data_preprocessing_library-0.1.0.dist-info/top_level.txt
data_preprocessing_library-0.1.0.dist-info/RECORD
