Metadata-Version: 2.1
Name: data_preprocessing_library
Version: 0.1.0
Summary: A comprehensive data preprocessing library for Python
Home-page: https://github.com/ayserragm/pythonProject
Author: Ayşe Serra
Author-email: ayseserra.gumustakim@stu.fsm.edu.tr
Classifier: Programming Language :: Python :: 3
Classifier: License :: OSI Approved :: MIT License
Classifier: Operating System :: OS Independent
Requires-Python: >=3.6
Requires-Dist: pandas
Requires-Dist: numpy
Requires-Dist: scikit-learn
Requires-Dist: nltk
